prainsa/__init__.py
prainsa/channel.py
prainsa/epoch.py
prainsa/prainsa.py
prainsa/speed_up.py
prainsa/utilities.py
prainsa/data/matlab_array_v6.mat
prainsa/data/matlab_array_v73.mat
prainsa/data/numpy_array.npy
prainsa/data/zipped_numpy_array.npz
prainsa/data/prainsa_object/bands.npz
prainsa/data/prainsa_object/dataset.npz
prainsa/data/prainsa_object/lags.npz
prainsa/data/prainsa_object/metadata.dat
prainsa/data/prainsa_object/xcorr.npz
prainsa/loader/__init__.py
prainsa/loader/loader.py
prainsa/loader/matlab_loader.py
prainsa/loader/numpy_loader.py
prainsa/loader/prainsa_loader.py
prainsa/plotly_plot/__init__.py
prainsa/plotly_plot/plotly_plot.py
prainsa-0.0.1.dist-info/DESCRIPTION.rst
prainsa-0.0.1.dist-info/METADATA
prainsa-0.0.1.dist-info/RECORD
prainsa-0.0.1.dist-info/WHEEL
prainsa-0.0.1.dist-info/metadata.json
prainsa-0.0.1.dist-info/top_level.txt
tests/__init__.py
tests/test_prainsa.py
