Metadata-Version: 2.0
Name: prainsa
Version: 0.0.1
Summary: A Python framework to analyze and visualize brain signals.
Home-page: https://github.com/A-Althobaiti/prainsa
Author: Abdulrahman A. Althobaiti
Author-email: Abdulrahman.Althobaiti@kaust.edu.sa
License: GNU General Public License v3
Keywords: prainsa
Platform: UNKNOWN
Classifier: Development Status :: 2 - Pre-Alpha
Classifier: Intended Audience :: Developers
Classifier: License :: OSI Approved :: GNU General Public License v3 (GPLv3)
Classifier: Natural Language :: English
Classifier: Programming Language :: Python :: 2.7
Classifier: Programming Language :: Python :: 3.4
Classifier: Programming Language :: Python :: 3.5
Classifier: Programming Language :: Python :: 3.6
Requires-Dist: h5py (>=2.6.0)
Requires-Dist: numpy (>=1.11.1)
Requires-Dist: plotly (>=2.0.12)
Requires-Dist: scipy (>=0.18.1)
